ezldap/__init__.py
ezldap/api.py
ezldap/config.py
ezldap/ldif.py
ezldap/password.py
ezldap/terminal.py
ezldap/version.py
ezldap/templates/add_group.ldif
ezldap/templates/add_host.ldif
ezldap/templates/add_to_group.ldif
ezldap/templates/add_user.ldif
ezldap-0.6.3.data/scripts/ezldap
ezldap-0.6.3.dist-info/METADATA
ezldap-0.6.3.dist-info/RECORD
ezldap-0.6.3.dist-info/WHEEL
ezldap-0.6.3.dist-info/top_level.txt
