Metadata-Version: 2.1
Name: ezldap
Version: 0.6.3
Summary: Scripts and Python bindings for easy LDAP operations.
Home-page: https://github.com/jstaf/ezldap
Author: Jeff Stafford
Author-email: jeff.stafford@queensu.ca
License: BSD3
Platform: UNKNOWN
Classifier: Programming Language :: Python :: 3.4
Classifier: Programming Language :: Python :: 3.5
Classifier: Programming Language :: Python :: 3.6
Classifier: Programming Language :: Python :: 3 :: Only
Classifier: Operating System :: POSIX :: Linux
Classifier: Operating System :: Unix
Classifier: Topic :: System :: Systems Administration :: Authentication/Directory :: LDAP
Classifier: License :: OSI Approved :: BSD License
Classifier: Development Status :: 4 - Beta
Requires-Dist: PyYAML
Requires-Dist: ldap3
